parser_cian
