Metadata-Version: 2.1
Name: parser-cian
Version: 0.1.5
Summary: Parser for easy data retrieval from cian.ru
Home-page: https://github.com/EZsmail/cian_parser
Author: Anatoly Gvozdev
Author-email: tolagvgvgvgv@gmail.com
License: MIT
Keywords: python parser requests cian realestate beautifulsoup dataset
Classifier: Programming Language :: Python :: 3
Classifier: License :: OSI Approved :: MIT License
Classifier: Operating System :: OS Independent
